migrations/__init__.py
xlsx_export/__init__.py
xlsx_export/admin.py
xlsx_export/apps.py
xlsx_export/forms.py
xlsx_export/models.py
xlsx_export/tests.py
xlsx_export/urls.py
xlsx_export/views.py
xlsx_export/migrations/__init__.py
xlsx_export/templates/success.html
xlsx_export/templates/upload.html
xlsx_export/templates/uploadxlsx.html
xlsx_export-0.0.30.dist-info/METADATA
xlsx_export-0.0.30.dist-info/WHEEL
xlsx_export-0.0.30.dist-info/entry_points.txt
xlsx_export-0.0.30.dist-info/top_level.txt
xlsx_export-0.0.30.dist-info/RECORD
