Metadata-Version: 2.1
Name: xlsx-export
Version: 0.0.30
Summary: Plugin for exporting test cases to XLSX format for TestY
Home-page: UNKNOWN
License: UNKNOWN
Platform: UNKNOWN
Requires-Dist: pandas
Requires-Dist: django
Requires-Dist: openpyxl
Requires-Dist: testy
